napari_copick/__init__.py
napari_copick/async_loaders.py
napari_copick/config_manager.py
napari_copick/data_loader.py
napari_copick/dialogs.py
napari_copick/gallery_widget.py
napari_copick/info_widget.py
napari_copick/napari.yaml
napari_copick/save_manager.py
napari_copick/save_utils.py
napari_copick/tree_expansion_manager.py
napari_copick/tree_widget.py
napari_copick/widget.py
napari_copick/_tests/__init__.py
napari_copick/_tests/test_widget.py
napari_copick/cli/__init__.py
napari_copick/cli/run.py
napari_copick-1.1.0.dist-info/METADATA
napari_copick-1.1.0.dist-info/WHEEL
napari_copick-1.1.0.dist-info/entry_points.txt
napari_copick-1.1.0.dist-info/licenses/LICENSE
napari_copick-1.1.0.dist-info/RECORD
