Metadata-Version: 2.4
Name: napari-copick
Version: 1.1.0
Summary: A plugin for collaborative annotation in cryoET using copick
Project-URL: Repository, https://github.com/kephale/napari-copick
Project-URL: Issues, https://github.com/kephale/napari-copick/issues
Project-URL: Documentation, https://github.com/kephale/napari-copick#README.md
Project-URL: Bug Tracker, https://github.com/kephale/napari-copick/issues
Project-URL: Source Code, https://github.com/kephale/napari-copick
Project-URL: User Support, https://github.com/kephale/napari-copick/issues
Author-email: Kyle Harrington <czi@kyleharrington.com>, "Utz H. Ermel" <utz.ermel@czii.org>
License: 
License-File: LICENSE
Keywords: annotation,copick,cryo-et,cryoet,napari,plugin,tomography
Classifier: Development Status :: 2 - Pre-Alpha
Classifier: Framework :: napari
Classifier: Intended Audience :: Developers
Classifier: License :: OSI Approved :: MIT License
Classifier: Operating System :: OS Independent
Classifier: Programming Language :: Python
Classifier: Programming Language :: Python :: 3
Classifier: Programming Language :: Python :: 3 :: Only
Classifier: Programming Language :: Python :: 3.9
Classifier: Programming Language :: Python :: 3.10
Classifier: Programming Language :: Python :: 3.11
Classifier: Programming Language :: Python :: 3.12
Classifier: Programming Language :: Python :: 3.13
Classifier: Programming Language :: Python :: Implementation :: CPython
Classifier: Programming Language :: Python :: Implementation :: PyPy
Classifier: Topic :: Scientific/Engineering :: Image Processing
Requires-Python: >=3.9
Requires-Dist: click
Requires-Dist: copick-shared-ui==0.2.0
Requires-Dist: copick>=1.6.0
Requires-Dist: fsspec
Requires-Dist: magicgui
Requires-Dist: napari
Requires-Dist: napari-ome-zarr
Requires-Dist: numpy
Requires-Dist: pydantic>=2
Requires-Dist: qtpy
Requires-Dist: scikit-image
Requires-Dist: trimesh
Requires-Dist: zarr
Provides-Extra: dev
Requires-Dist: black>=25.1.0; extra == 'dev'
Requires-Dist: hatch-vcs>=0.4.0; extra == 'dev'
Requires-Dist: hatchling>=1.25.0; extra == 'dev'
Requires-Dist: pre-commit>=4.2.0; extra == 'dev'
Requires-Dist: ruff>=0.12.0; extra == 'dev'
Provides-Extra: testing
Requires-Dist: napari; extra == 'testing'
Requires-Dist: pyqt6; extra == 'testing'
Requires-Dist: pytest; extra == 'testing'
Requires-Dist: pytest-cov; extra == 'testing'
Requires-Dist: pytest-qt; extra == 'testing'
Requires-Dist: tox; extra == 'testing'
Requires-Dist: tox-gh-actions; extra == 'testing'
Requires-Dist: tox-uv; extra == 'testing'
